a_pandas_ex_multimerge/LICENSE
a_pandas_ex_multimerge/README.MD
a_pandas_ex_multimerge/__init__.py
a_pandas_ex_multimerge/requirements.txt
a_pandas_ex_multimerge/thirdparty.json
a_pandas_ex_multimerge-0.10.dist-info/LICENSE.rst
a_pandas_ex_multimerge-0.10.dist-info/METADATA
a_pandas_ex_multimerge-0.10.dist-info/WHEEL
a_pandas_ex_multimerge-0.10.dist-info/top_level.txt
a_pandas_ex_multimerge-0.10.dist-info/RECORD
