Metadata-Version: 2.1
Name: a-pandas-ex-multimerge
Version: 0.10
Summary: Merges multiple DataFrames, ignores Exceptions if desired
Home-page: https://github.com/hansalemaos/a_pandas_ex_multimerge
Author: Johannes Fischer
Author-email: <aulasparticularesdealemaosp@gmail.com>
License: MIT
Keywords: group,intersections,DataFrame,merge,concat
Classifier: Development Status :: 4 - Beta
Classifier: Programming Language :: Python :: 3 :: Only
Classifier: Programming Language :: Python :: 3.9
Classifier: Topic :: Scientific/Engineering :: Visualization
Classifier: Topic :: Software Development :: Libraries :: Python Modules
Classifier: Topic :: Text Editors :: Text Processing
Classifier: Topic :: Text Processing :: General
Classifier: Topic :: Text Processing :: Indexing
Classifier: Topic :: Text Processing :: Filters
Classifier: Topic :: Utilities
License-File: LICENSE.rst
Requires-Dist: flexible-partial
Requires-Dist: pandas
Requires-Dist: useful-functions-easier-life
